skinsegmentator/__init__.py
skinsegmentator/alignment.py
skinsegmentator/config.py
skinsegmentator/cropping.py
skinsegmentator/dicom_io.py
skinsegmentator/libs.py
skinsegmentator/map_to_binary.py
skinsegmentator/nifti_ext_header.py
skinsegmentator/nnunet.py
skinsegmentator/postprocessing.py
skinsegmentator/python_api.py
skinsegmentator/resampling.py
skinsegmentator/bin/SkinSegmentator.py
skinsegmentator/bin/__init__.py
skinsegmentator/weights/__init__.py
SkinSegmentator-1.2.0.dist-info/LICENSE
SkinSegmentator-1.2.0.dist-info/METADATA
SkinSegmentator-1.2.0.dist-info/WHEEL
SkinSegmentator-1.2.0.dist-info/entry_points.txt
SkinSegmentator-1.2.0.dist-info/top_level.txt
SkinSegmentator-1.2.0.dist-info/RECORD
