Metadata-Version: 2.1
Name: SkinSegmentator
Version: 1.2.0
Summary: Robust segmentation of skin surface in MR images.
Home-page: https://github.com/reubendo/SkinSegmentator
Author: Reuben Dorent
Author-email: rdorent@bwh.harvard.edu
License: MIT
Classifier: Intended Audience :: Science/Research
Classifier: Programming Language :: Python
Classifier: Topic :: Scientific/Engineering
Classifier: Operating System :: Unix
Classifier: Operating System :: MacOS
Requires-Python: >=3.9
License-File: LICENSE
Requires-Dist: torch >=2.0.0
Requires-Dist: numpy
Requires-Dist: psutil
Requires-Dist: SimpleITK
Requires-Dist: nibabel >=2.3.0
Requires-Dist: tqdm >=4.45.0
Requires-Dist: p-tqdm
Requires-Dist: xvfbwrapper
Requires-Dist: fury
Requires-Dist: nnunetv2 >=2.2.1
Requires-Dist: requests
Requires-Dist: rt-utils
Requires-Dist: dicom2nifti
Requires-Dist: pyarrow
